sshplex/__init__.py
sshplex/cli.py
sshplex/config-template.yaml
sshplex/main.py
sshplex/sshplex_connector.py
sshplex/lib/__init__.py
sshplex/lib/cache.py
sshplex/lib/config.py
sshplex/lib/logger.py
sshplex/lib/multiplexer/__init__.py
sshplex/lib/multiplexer/base.py
sshplex/lib/multiplexer/tmux.py
sshplex/lib/sot/__init__.py
sshplex/lib/sot/ansible.py
sshplex/lib/sot/base.py
sshplex/lib/sot/factory.py
sshplex/lib/sot/netbox.py
sshplex/lib/sot/static.py
sshplex/lib/ssh/__init__.py
sshplex/lib/ssh/connection.py
sshplex/lib/ssh/manager.py
sshplex/lib/ui/__init__.py
sshplex/lib/ui/host_selector.py
sshplex/lib/ui/session_manager.py
sshplex-1.0.19.dist-info/licenses/LICENSE
sshplex-1.0.19.dist-info/METADATA
sshplex-1.0.19.dist-info/WHEEL
sshplex-1.0.19.dist-info/entry_points.txt
sshplex-1.0.19.dist-info/top_level.txt
sshplex-1.0.19.dist-info/RECORD
