Metadata-Version: 2.4
Name: sshplex
Version: 1.0.19
Summary: Multiplex your SSH connections with style
Author-email: MJAHED Sabri <contact@sabrimjahed.com>
License: MIT
Project-URL: Homepage, https://github.com/sabrimjd/sshplex
Project-URL: Repository, https://github.com/sabrimjd/sshplex
Project-URL: Documentation, https://github.com/sabrimjd/sshplex#readme
Project-URL: Bug Tracker, https://github.com/sabrimjd/sshplex/issues
Keywords: ssh,tmux,multiplexer,netbox,tui,terminal
Classifier: Development Status :: 4 - Beta
Classifier: Environment :: Console
Classifier: Intended Audience :: Developers
Classifier: Intended Audience :: System Administrators
Classifier: License :: OSI Approved :: MIT License
Classifier: Operating System :: POSIX :: Linux
Classifier: Operating System :: MacOS
Classifier: Programming Language :: Python :: 3
Classifier: Programming Language :: Python :: 3.8
Classifier: Programming Language :: Python :: 3.9
Classifier: Programming Language :: Python :: 3.10
Classifier: Programming Language :: Python :: 3.11
Classifier: Programming Language :: Python :: 3.12
Classifier: Topic :: System :: Networking
Classifier: Topic :: System :: Systems Administration
Classifier: Topic :: Terminals
Requires-Python: >=3.8
License-File: LICENSE
Requires-Dist: pynetbox==7.5.0
Requires-Dist: textual==3.3.0
Requires-Dist: pyyaml==6.0.2
Requires-Dist: pydantic==2.11.0
Requires-Dist: loguru==0.7.3
Requires-Dist: rich==13.9.4
Requires-Dist: libtmux==0.46.1
Provides-Extra: dev
Requires-Dist: pytest>=7.0.0; extra == "dev"
Requires-Dist: pytest-cov>=4.0.0; extra == "dev"
Requires-Dist: black>=22.0.0; extra == "dev"
Requires-Dist: flake8>=5.0.0; extra == "dev"
Requires-Dist: mypy>=1.0.0; extra == "dev"
Requires-Dist: types-PyYAML>=6.0.0; extra == "dev"
Dynamic: license-file
